setup.py
gril/__init__.py
gril/gril.py
gril.egg-info/PKG-INFO
gril.egg-info/SOURCES.txt
gril.egg-info/dependency_links.txt
gril.egg-info/top_level.txt